{
	"name": "ds_github",
	"properties": {
		"linkedServiceName": {
			"referenceName": "Is_github",
			"type": "LinkedServiceReference"
		},
		"parameters": {
			"file_name": {
				"type": "string",
				"defaultValue": "Cars.csv"
			}
		},
		"annotations": [],
		"type": "DelimitedText",
		"typeProperties": {
			"location": {
				"type": "HttpServerLocation",
				"relativeUrl": {
					"value": "Pokala-Vasanth-Kumar/DataEng/refs/heads/main/@{dataset().file_name}",
					"type": "Expression"
				}
			},
			"columnDelimiter": ",",
			"rowDelimiter": "\n",
			"escapeChar": "\\",
			"firstRowAsHeader": true,
			"quoteChar": "\""
		},
		"schema": []
	}
}